long_net/__init__.py
long_net/attention.py
long_net/model.py
long_net/utils.py
longnet-0.5.7.dist-info/LICENSE
longnet-0.5.7.dist-info/WHEEL
longnet-0.5.7.dist-info/METADATA
longnet-0.5.7.dist-info/RECORD
