Metadata-Version: 2.1
Name: longnet
Version: 0.5.7
Summary: LongNet - Pytorch
Home-page: https://github.com/kyegomez/LongNet
License: MIT
Keywords: artificial intelligence,deep learning,optimizers,Prompt Engineering
Author: Kye Gomez
Author-email: kye@apac.ai
Requires-Python: >=3.6,<4.0
Classifier: Development Status :: 4 - Beta
Classifier: Intended Audience :: Developers
Classifier: License :: OSI Approved :: MIT License
Classifier: Programming Language :: Python :: 3
Classifier: Programming Language :: Python :: 3.6
Classifier: Programming Language :: Python :: 3.7
Classifier: Programming Language :: Python :: 3.8
Classifier: Programming Language :: Python :: 3.9
Classifier: Programming Language :: Python :: 3.10
Classifier: Programming Language :: Python :: 3.11
Classifier: Programming Language :: Python :: 3.6
Classifier: Topic :: Scientific/Engineering :: Artificial Intelligence
Requires-Dist: accelerate
Requires-Dist: beartype
Requires-Dist: bitsandbytes
Requires-Dist: dataclasses
Requires-Dist: einops
Requires-Dist: torch
Requires-Dist: torchscale
Requires-Dist: transformers
Requires-Dist: zetascale
Project-URL: Documentation, https://github.com/kyegomez/LongNet
Project-URL: Repository, https://github.com/kyegomez/LongNet
